rfpye/__init__.py
rfpye/_nbdev.py
rfpye/blocks.py
rfpye/constants.py
rfpye/cyparser.c
rfpye/cyparser.cp39-win_amd64.pyd
rfpye/cyparser.pyx
rfpye/parser.py
rfpye/utils.py
rfpye-0.3.7.dist-info/LICENSE
rfpye-0.3.7.dist-info/METADATA
rfpye-0.3.7.dist-info/WHEEL
rfpye-0.3.7.dist-info/entry_points.txt
rfpye-0.3.7.dist-info/top_level.txt
rfpye-0.3.7.dist-info/RECORD
