Metadata-Version: 2.1
Name: rfpye
Version: 0.3.7
Summary: Binary Files Parser resulted from the script Logger from CRFS - Rfeye Node Equipament
Home-page: https://github.com/ronaldokun/rfpye/tree/master/
Author: Ronaldo Batista
Author-email: ronaldokun@gmail.com
License: Apache Software License 2.0
Keywords: spectrum monitoring
Platform: UNKNOWN
Classifier: Development Status :: 4 - Beta
Classifier: Intended Audience :: Developers
Classifier: License :: OSI Approved :: Apache Software License
Classifier: Natural Language :: Portuguese
Classifier: Programming Language :: Python :: 3.8
Classifier: Programming Language :: Python :: 3.9
Requires-Python: >=3.8
License-File: LICENSE
Requires-Dist: Cython
Requires-Dist: numpy
Requires-Dist: fastcore
Requires-Dist: feather-format
Requires-Dist: pandas
Requires-Dist: rich
Requires-Dist: openpyxl
Requires-Dist: loguru
Provides-Extra: dev
Requires-Dist: nbdev (>=1.1.3) ; extra == 'dev'
Requires-Dist: mypy ; extra == 'dev'
Requires-Dist: black ; extra == 'dev'
Requires-Dist: twine ; extra == 'dev'
